langchain_pangea-0.1.6.dist-info/METADATA
langchain_pangea-0.1.6.dist-info/WHEEL
langchain_pangea-0.1.6.dist-info/entry_points.txt
langchain_pangea-0.1.6.dist-info/licenses/LICENSE
langchain_pangea/__init__.py
langchain_pangea/document_transformers/pangea_text_guard.py
langchain_pangea/py.typed
langchain_pangea/tools/ai_guard.py
langchain_pangea/tools/base.py
langchain_pangea/tools/domain_intel_guard.py
langchain_pangea/tools/ip_intel_guard.py
langchain_pangea/tools/prompt_guard.py
langchain_pangea/tools/redact_guard.py
langchain_pangea/tools/url_intel_guard.py
langchain_pangea/tracers/pangea_audit_log_tracer.py
langchain_pangea-0.1.6.dist-info/RECORD
