Metadata-Version: 2.4
Name: langchain-pangea
Version: 0.1.6
Summary: LangChain integrations for Pangea
Author-Email: Pangea <support@pangea.cloud>
License-Expression: MIT
Project-URL: Source Code, https://github.com/pangeacyber/langchain-pangea
Project-URL: Release Notes, https://github.com/pangeacyber/langchain-pangea/releases
Requires-Python: >=3.11
Requires-Dist: langchain-core>=0.3.75
Requires-Dist: pangea-sdk>=6.6.0
Requires-Dist: pydantic>=2.11.7
Requires-Dist: typing-extensions>=4.15.0
